sphinxcontrib/images.py
sphinxcontrib_images-1.0.0.dist-info/licenses/LICENSE.txt
sphinxcontrib_images_lightbox2/__init__.py
sphinxcontrib_images_lightbox2/lightbox2.py
sphinxcontrib_images_lightbox2/lightbox2/dist/css/lightbox.min.css
sphinxcontrib_images_lightbox2/lightbox2/dist/images/close.png
sphinxcontrib_images_lightbox2/lightbox2/dist/images/loading.gif
sphinxcontrib_images_lightbox2/lightbox2/dist/images/next.png
sphinxcontrib_images_lightbox2/lightbox2/dist/images/prev.png
sphinxcontrib_images_lightbox2/lightbox2/dist/js/lightbox-plus-jquery.min.js
sphinxcontrib_images_lightbox2/lightbox2/dist/js/lightbox-plus-jquery.min.map
sphinxcontrib_images_lightbox2/lightbox2-customize/jquery-noconflict.js
sphinxcontrib_images_lightbox2/lightbox2-customize/pointer.css
sphinxcontrib_images-1.0.0.dist-info/METADATA
sphinxcontrib_images-1.0.0.dist-info/WHEEL
sphinxcontrib_images-1.0.0.dist-info/entry_points.txt
sphinxcontrib_images-1.0.0.dist-info/top_level.txt
sphinxcontrib_images-1.0.0.dist-info/RECORD
