Metadata-Version: 2.4
Name: sphinxcontrib-images
Version: 1.0.0
Summary: Sphinx extension for thumbnails
Author-email: Tomasz Czyż <tomasz.czyz@gmail.com>
License-Expression: Apache-2.0
Project-URL: Documentation, https://sphinxcontrib-images.readthedocs.io/
Project-URL: Download, https://pypi.python.org/pypi/sphinxcontrib-images
Project-URL: Issues, https://github.com/sphinx-contrib/images/issues
Project-URL: Repository, https://github.com/sphinx-contrib/images
Classifier: Development Status :: 4 - Beta
Classifier: Environment :: Console
Classifier: Environment :: Web Environment
Classifier: Intended Audience :: Developers
Classifier: Operating System :: OS Independent
Classifier: Programming Language :: Python
Classifier: Programming Language :: Python :: 3 :: Only
Classifier: Programming Language :: Python :: 3.9
Classifier: Programming Language :: Python :: 3.10
Classifier: Programming Language :: Python :: 3.11
Classifier: Programming Language :: Python :: 3.12
Classifier: Programming Language :: Python :: 3.13
Classifier: Topic :: Documentation
Requires-Python: >=3.9
License-File: LICENSE.txt
Requires-Dist: requests<3,>2.2
Requires-Dist: sphinx>=5.0
Dynamic: license-file
